LICENSE
MANIFEST.in
README
setup.py
django_cms_jplayer.egg-info/PKG-INFO
django_cms_jplayer.egg-info/SOURCES.txt
django_cms_jplayer.egg-info/dependency_links.txt
django_cms_jplayer.egg-info/not-zip-safe
django_cms_jplayer.egg-info/top_level.txt
jplayer/__init__.py
jplayer/admin.py
jplayer/cms_plugins.py
jplayer/models.py
jplayer/utils.py
jplayer/media/jplayer/js/cmsplayer.js
jplayer/migrations/0001_initial.py
jplayer/migrations/__init__.py
jplayer/templates/jplayer/player.html
jplayer/templates/jplayer/player_base.html
jplayer/templates/jplayer/song.html
jplayer/templatetags/__init__.py
jplayer/templatetags/jplayer_tags.py