Metadata-Version: 1.0
Name: django-cms-jplayer
Version: 0.1.10
Summary: Django-CMS JPlayer Plugin
Home-page: http://github.com/ojii/django-cms-jplayer
Author: Jonas Obrist
Author-email: jonas.obrist@divio.ch
License: UNKNOWN
Platform: UNKNOWN
